LICENSE
README.md
setup.py
brainscore/__init__.py
brainscore/entrypoint.py
brainscore/model_interface.py
brainscore/benchmarks/__init__.py
brainscore/benchmarks/_neural_common.py
brainscore/benchmarks/_properties_common.py
brainscore/benchmarks/cadena2017.py
brainscore/benchmarks/freemanziemba2013.py
brainscore/benchmarks/geirhos2021.py
brainscore/benchmarks/hermann2020.py
brainscore/benchmarks/imagenet.py
brainscore/benchmarks/imagenet_c.py
brainscore/benchmarks/islam2021.py
brainscore/benchmarks/kar2019.py
brainscore/benchmarks/majajhong2015.py
brainscore/benchmarks/marques2020_cavanaugh2002a.py
brainscore/benchmarks/marques2020_devalois1982a.py
brainscore/benchmarks/marques2020_devalois1982b.py
brainscore/benchmarks/marques2020_freemanZiemba2013.py
brainscore/benchmarks/marques2020_ringach2002.py
brainscore/benchmarks/marques2020_schiller1976.py
brainscore/benchmarks/objectnet.py
brainscore/benchmarks/public_benchmarks.py
brainscore/benchmarks/rajalingham2018.py
brainscore/benchmarks/rajalingham2020.py
brainscore/benchmarks/sanghavi2020.py
brainscore/benchmarks/sanghavijozwik2020.py
brainscore/benchmarks/sanghavimurty2020.py
brainscore/benchmarks/screen.py
brainscore/metrics/__init__.py
brainscore/metrics/accuracy.py
brainscore/metrics/anatomy.py
brainscore/metrics/ceiling.py
brainscore/metrics/cka.py
brainscore/metrics/correlation.py
brainscore/metrics/dimensionality.py
brainscore/metrics/distribution_similarity.py
brainscore/metrics/error_consistency.py
brainscore/metrics/image_level_behavior.py
brainscore/metrics/mask_regression.py
brainscore/metrics/ost.py
brainscore/metrics/rdm.py
brainscore/metrics/regression.py
brainscore/metrics/temporal.py
brainscore/metrics/transformations.py
brainscore/metrics/utils.py
brainscore/metrics/xarray_utils.py
brainscore/submission/__init__.py
brainscore/submission/__main__.py
brainscore/submission/configuration.py
brainscore/submission/database.py
brainscore/submission/evaluation.py
brainscore/submission/ml_pool.py
similarity_repository.egg-info/PKG-INFO
similarity_repository.egg-info/SOURCES.txt
similarity_repository.egg-info/dependency_links.txt
similarity_repository.egg-info/requires.txt
similarity_repository.egg-info/top_level.txt