Metadata-Version: 2.1
Name: similarity-repository
Version: 0.0.1
Summary: A repository for similarity measures.
Home-page: UNKNOWN
Author: Nathan Cloos
License: UNKNOWN
Platform: UNKNOWN
License-File: LICENSE
